{"64001":["LT","64001","Kani\u016bk\u0173 k.","Alytus County","56","Alytaus r. sav.","33","","","54.3667","24.3333","1"],"64005":["LT","64005","Laukinink\u0173 k.","Alytus County","56","Alytaus r. sav.","33","","","54.3667","24.3333","1"],"64009":["LT","64009","Vaikantoni\u0173 k.","Alytus County","56","Alytaus r. sav.","33","","","54.3667","24.3333","3"],"64017":["LT","64017","Mie\u017eioni\u0173 k.","Alytus County","56","Alytaus r. sav.","33","","","54.4","24.0067","1"],"64021":["LT","64021","Geis\u010di\u016bn\u0173 k.","Alytus County","56","Alytaus r. sav.","33","","","54.3","24.0333","3"],"64025":["LT","64025","Arci\u0161koni\u0173 k.","Alytus County","56","Alytaus r. sav.","33","","","54.3","24.0333","1"],"64029":["LT","64029","Kauk\u0173 l k.","Alytus County","56","Alytaus r. sav.","33","","","54.3","24.0333","1"],"64037":["LT","64037","Aleknoni\u0173 k.","Alytus County","56","Alytaus r. sav.","33","","","54.4","23.65","3"],"64041":["LT","64041","Verebiej\u0173 k.","Alytus County","56","Alytaus r. sav.","33","","","54.4333","23.7667","3"],"64045":["LT","64045","Cibiliek\u0173 k.","Alytus County","56","Alytaus r. sav.","33","","","54.4333","23.7667","1"],"64053":["LT","64053","Vytauti\u0161ki\u0173 k.","Alytus County","56","Alytaus r. sav.","33","","","54.4","24.0067","1"],"64057":["LT","64057","Striel\u010di\u0173 k.","Alytus County","56","Alytaus r. sav.","33","","","54.4","24.0067","1"],"64061":["LT","64061","Trakinink\u0173 k.","Alytus County","56","Alytaus r. sav.","33","","","54.5","24.25","3"],"64065":["LT","64065","Jurkioni\u0173 k.","Alytus County","56","Alytaus r. sav.","33","","","54.5","24.25","1"],"64069":["LT","64069","Pa\u0161ilio k.","Alytus County","56","Alytaus r. sav.","33","","","54.5","24.25","1"]}